imer4x_demo/__init__.py
imer4x_demo/main.py
imer4x_demo-0.1.0.dist-info/METADATA
imer4x_demo-0.1.0.dist-info/WHEEL
imer4x_demo-0.1.0.dist-info/RECORD
